pykagapi/__init__.py
pykagapi/core/__init__.py
pykagapi/core/async_client.py
pykagapi/core/client.py
pykagapi/kag/__init__.py
pykagapi/kag/async_client.py
pykagapi/kag/async_extra.py
pykagapi/kag/client.py
pykagapi/kag/extra.py
pykagapi/kagstats/__init__.py
pykagapi/kagstats/async_client.py
pykagapi/kagstats/client.py
pykagapi-0.4.0.dist-info/LICENSE
pykagapi-0.4.0.dist-info/METADATA
pykagapi-0.4.0.dist-info/WHEEL
pykagapi-0.4.0.dist-info/RECORD
