Metadata-Version: 2.1
Name: pykagapi
Version: 0.4.0
Summary: pykagapi - python wrapper for King Arthur's Gold-related APIs
Home-page: https://github.com/moonburnt/pykagapi
License: MIT
Author: moonburnt
Author-email: moonburnt@disroot.org
Requires-Python: >=3.10,<4.0
Classifier: License :: OSI Approved :: MIT License
Classifier: Programming Language :: Python :: 3
Classifier: Programming Language :: Python :: 3.10
Classifier: Programming Language :: Python :: 3.11
Requires-Dist: aiohttp (>=3.8.6,<4.0.0)
Requires-Dist: requests (>=2.31.0,<3.0.0)
